personalNotion/__init__.py
personalNotion/database.py
personalNotion/page.py
personalNotion/table.py
personalNotion/test.py
personalNotion-1.5.1.dist-info/METADATA
personalNotion-1.5.1.dist-info/WHEEL
personalNotion-1.5.1.dist-info/entry_points.txt
personalNotion-1.5.1.dist-info/top_level.txt
personalNotion-1.5.1.dist-info/RECORD
