Metadata-Version: 2.1
Name: personalNotion
Version: 1.5.1
Summary: All functions that assist in standardising development approaches.
Home-page: https://github.com/yourusername/your-repo
Author: Marcus
Author-email: marcusongkiansiong@gmail.com
Classifier: Programming Language :: Python :: 3
Classifier: License :: OSI Approved :: MIT License
Classifier: Operating System :: OS Independent
Requires-Python: >=3.6
Requires-Dist: custom-development-standardisation >=1.1.2
Requires-Dist: log-data >=1.2.0
Requires-Dist: python-dotenv >=1.0.1
Requires-Dist: Requests >=2.32.3
